LICENSE
MANIFEST.in
setup.cfg
setup.py
Wappium_Python_Client.egg-info/PKG-INFO
Wappium_Python_Client.egg-info/SOURCES.txt
Wappium_Python_Client.egg-info/dependency_links.txt
Wappium_Python_Client.egg-info/requires.txt
Wappium_Python_Client.egg-info/top_level.txt
appium/__init__.py
appium/saucetestcase.py
appium/common/__init__.py
appium/common/exceptions.py
appium/webdriver/__init__.py
appium/webdriver/connectiontype.py
appium/webdriver/errorhandler.py
appium/webdriver/mobilecommand.py
appium/webdriver/switch_to.py
appium/webdriver/webdriver.py
appium/webdriver/webelement.py
appium/webdriver/common/__init__.py
appium/webdriver/common/mobileby.py
appium/webdriver/common/multi_action.py
appium/webdriver/common/touch_action.py
docs/roadmap.md