Metadata-Version: 1.1
Name: Wappium-Python-Client
Version: 1.0
Summary: Python client for Wappium 1.6
Home-page: http://www.testwa.com/
Author: Xin Yang
Author-email: yx_yoyo@live.cn
License: Apache 2.0
Keywords: appium,appium 1.0,selenium,selenium 3,python client,mobile automation
Platform: UNKNOWN
Classifier: Development Status :: 3 - Alpha
Classifier: Programming Language :: Python
Classifier: Environment :: Console
Classifier: Environment :: MacOS X
Classifier: Environment :: Win32 (MS Windows)
Classifier: Intended Audience :: Developers
Classifier: Intended Audience :: Other Audience
Classifier: License :: OSI Approved :: Apache Software License
Classifier: Operating System :: OS Independent
Classifier: Topic :: Software Development :: Quality Assurance
Classifier: Topic :: Software Development :: Testing
